markji/__init__.py
markji/_const.py
markji/_response.py
markji/auth.py
markji/editor/__init__.py
markji/editor/choice.py
markji/editor/cloze.py
markji/editor/font.py
markji/editor/formula.py
markji/editor/media.py
markji/editor/paragraph.py
markji/editor/reference.py
markji/types/__init__.py
markji/types/_form.py
markji/types/card.py
markji/types/chapter.py
markji/types/deck.py
markji/types/folder.py
markji/types/user.py
markji-0.1.1.dist-info/LICENSE
markji-0.1.1.dist-info/METADATA
markji-0.1.1.dist-info/WHEEL
markji-0.1.1.dist-info/RECORD
