Metadata-Version: 2.1
Name: markji
Version: 0.1.1
Summary: Markji SDK for Python
Home-page: https://github.com/hlf20010508/markji-py/tree/master
License: MIT
Keywords: markji,sdk,python
Author: L-ING
Author-email: hlf01@icloud.com
Requires-Python: >=3.11,<4.0
Classifier: License :: OSI Approved :: MIT License
Classifier: Programming Language :: Python :: 3
Classifier: Programming Language :: Python :: 3.11
Classifier: Programming Language :: Python :: 3.12
Classifier: Programming Language :: Python :: 3.13
Classifier: Topic :: Software Development :: Libraries :: Python Modules
Requires-Dist: aiohttp (>=3.11.14,<4.0.0)
Requires-Dist: dataclasses-json (>=0.6.7,<0.7.0)
Project-URL: Documentation, https://hlf20010508.github.io/markji-py/
Project-URL: Repository, https://github.com/hlf20010508/markji-py/tree/master
